openimis_be_policy-1.10.0.dist-info/licenses/LICENSE.md
policy/__init__.py
policy/admin.py
policy/apps.py
policy/gql_mutations.py
policy/gql_queries.py
policy/models.py
policy/report.py
policy/schema.py
policy/services.py
policy/signals.py
policy/tasks.py
policy/test_helpers.py
policy/urls.py
policy/utils.py
policy/validations.py
policy/values.py
policy/views.py
policy/migrations/0001_initial.py
policy/migrations/0002_policy_renewals.py
policy/migrations/0003_auto_20201021_0811.py
policy/migrations/0004_add_medical_oficer_reading_rights.py
policy/migrations/0005_add_foreign_keys.py
policy/migrations/0006_set_model_managed_to_true.py
policy/migrations/0007_fix_policy_mutation_name.py
policy/migrations/0008_policyrenewalmutation.py
policy/migrations/0008_remove_policy_row_id_policy_contribution_plan.py
policy/migrations/0009_auto_20240716_1744.py
policy/migrations/0010_merge_20240912_1248.py
policy/migrations/0011_policyrenewal_unique_policy_validity_to_null.py
policy/migrations/__init__.py
policy/reports/__init__.py
policy/reports/policy_renewals.py
policy/reports/primary_operational_indicators.py
policy/tests/__init__.py
policy/tests/test_services.py
policy/tests/test_values.py
policy/tests/tests.py
policy/tests/tests_gql.py
policy/tests/tests_reports.py
openimis_be_policy-1.10.0.dist-info/METADATA
openimis_be_policy-1.10.0.dist-info/WHEEL
openimis_be_policy-1.10.0.dist-info/top_level.txt
openimis_be_policy-1.10.0.dist-info/RECORD
